LICENSE.txt
MANIFEST.in
README.rst
distribute_setup.py
setup.py
docs/conf.py
docs/index.rst
rst2blogger/__init__.py
rst2blogger/cli.py
rst2blogger/rst2post.py
rst2blogger.egg-info/PKG-INFO
rst2blogger.egg-info/SOURCES.txt
rst2blogger.egg-info/dependency_links.txt
rst2blogger.egg-info/entry_points.txt
rst2blogger.egg-info/not-zip-safe
rst2blogger.egg-info/requires.txt
rst2blogger.egg-info/top_level.txt
tests/test_rst2post.py
tests/test_rst2post.pyc