Metadata-Version: 1.1
Name: rst2blogger
Version: 1.0.1
Summary: Convert reStructuredText to HTML then post on Blogger.com blogs
Home-page: http://www.doughellmann.com/projects/rst2blogger/
Author: Doug Hellmann
Author-email: doug.hellmann@gmail.com
License: BSD
Platform: Any
Classifier: Development Status :: 4 - Beta
Classifier: License :: OSI Approved :: BSD License
Classifier: Programming Language :: Python
Classifier: Programming Language :: Python :: 2
Classifier: Programming Language :: Python :: 2.7
Classifier: Environment :: Console
Provides: rst2blogger
